{
    "%vlocity_namespace%__DestinationFieldName__c": "%vlocity_namespace%__RecurringUOM__c",
    "%vlocity_namespace%__DestinationSObjectType__c": "OrderItem",
    "%vlocity_namespace%__SourceFieldName__c": "%vlocity_namespace%__RecurringUOM__c",
    "%vlocity_namespace%__SourceFieldSObjectType__c": "",
    "%vlocity_namespace%__SourceFieldType__c": "picklist",
    "%vlocity_namespace%__SourceSObjectType__c": "Asset",
    "Name": "Asset>OrderItem1",
    "VlocityDataPackType": "SObject",
    "VlocityRecordSObjectType": "%vlocity_namespace%__CustomFieldMap__c",
    "VlocityRecordSourceKey": "%vlocity_namespace%__CustomFieldMap__c/Asset>OrderItem1"
}