[
    {
        "FilterGroup": 0,
        "FilterOperator": "=",
        "FilterValue": "contextId",
        "GlobalKey": "UniversityCustom2124",
        "InputFieldName": "Id",
        "InputObjectName": "Account",
        "InputObjectQuerySequence": 1,
        "IsDisabled": false,
        "IsRequiredForUpsert": false,
        "IsUpsertKey": false,
        "Name": "University",
        "OmniDataTransformationId": {
            "Name": "University",
            "VlocityDataPackType": "VlocityMatchingKeyObject",
            "VlocityMatchingRecordSourceKey": "OmniDataTransform/University",
            "VlocityRecordSObjectType": "OmniDataTransform"
        },
        "OutputCreationSequence": 0,
        "OutputFieldName": "account",
        "OutputObjectName": "json",
        "VlocityDataPackType": "SObject",
        "VlocityRecordSObjectType": "OmniDataTransformItem"
    },
    {
        "GlobalKey": "UniversityCustom5737",
        "InputFieldName": "account:Name",
        "IsDisabled": false,
        "IsRequiredForUpsert": false,
        "IsUpsertKey": false,
        "Name": "University",
        "OmniDataTransformationId": {
            "Name": "University",
            "VlocityDataPackType": "VlocityMatchingKeyObject",
            "VlocityMatchingRecordSourceKey": "OmniDataTransform/University",
            "VlocityRecordSObjectType": "OmniDataTransform"
        },
        "OutputCreationSequence": 1,
        "OutputFieldName": "NAME",
        "OutputObjectName": "json",
        "VlocityDataPackType": "SObject",
        "VlocityRecordSObjectType": "OmniDataTransformItem"
    },
    {
        "GlobalKey": "UniversityCustom7900",
        "InputFieldName": "account:Phone",
        "IsDisabled": false,
        "IsRequiredForUpsert": false,
        "IsUpsertKey": false,
        "Name": "University",
        "OmniDataTransformationId": {
            "Name": "University",
            "VlocityDataPackType": "VlocityMatchingKeyObject",
            "VlocityMatchingRecordSourceKey": "OmniDataTransform/University",
            "VlocityRecordSObjectType": "OmniDataTransform"
        },
        "OutputCreationSequence": 1,
        "OutputFieldName": "phone",
        "OutputObjectName": "json",
        "VlocityDataPackType": "SObject",
        "VlocityRecordSObjectType": "OmniDataTransformItem"
    }
]