{
    "%vlocity_namespace%__DestinationFieldName__c": "%vlocity_namespace%__FrameContractId__c",
    "%vlocity_namespace%__DestinationSObjectType__c": "Quote",
    "%vlocity_namespace%__SourceFieldName__c": "%vlocity_namespace%__FrameContractId__c",
    "%vlocity_namespace%__SourceFieldSObjectType__c": "Contract",
    "%vlocity_namespace%__SourceFieldType__c": "reference",
    "%vlocity_namespace%__SourceSObjectType__c": "Opportunity",
    "Name": "Opportunity>Quote4",
    "VlocityDataPackType": "SObject",
    "VlocityRecordSObjectType": "%vlocity_namespace%__CustomFieldMap__c",
    "VlocityRecordSourceKey": "%vlocity_namespace%__CustomFieldMap__c/Opportunity>Quote4"
}