{
    "%vlocity_namespace%__ApprovedBy__c": "",
    "%vlocity_namespace%__ApprovedOn__c": "",
    "%vlocity_namespace%__AttributeDefaultValues__c": "",
    "%vlocity_namespace%__AttributeMetadata__c": "",
    "%vlocity_namespace%__AttributeRules__c": "",
    "%vlocity_namespace%__CategoryData__c": "",
    "%vlocity_namespace%__ChangeDetectorImplementation__c": "",
    "%vlocity_namespace%__ClassId__c": "",
    "%vlocity_namespace%__DefaultImageId__c": "",
    "%vlocity_namespace%__EffectiveDate__c": "2017-09-01",
    "%vlocity_namespace%__EndDate__c": "",
    "%vlocity_namespace%__EndOfLifeDate__c": "",
    "%vlocity_namespace%__FulfilmentStartDate__c": "2017-09-01T07:00:00.000Z",
    "%vlocity_namespace%__GlobalGroupKey__c": "bdfd494e-2cc2-f552-5345-51ed9af35f1a",
    "%vlocity_namespace%__GlobalKey__c": "147500f4-1fce-bca1-e77b-d684c5441e1f",
    "%vlocity_namespace%__HeaderData__c": "",
    "%vlocity_namespace%__HelpText__c": "",
    "%vlocity_namespace%__IsConfigurable__c": false,
    "%vlocity_namespace%__IsLocationDependent__c": false,
    "%vlocity_namespace%__IsNotAssetizable__c": false,
    "%vlocity_namespace%__IsOrderable__c": true,
    "%vlocity_namespace%__JeopardySafetyIntervalUnit__c": "",
    "%vlocity_namespace%__JeopardySafetyInterval__c": "",
    "%vlocity_namespace%__LifecycleStatus__c": "",
    "%vlocity_namespace%__Modification__c": "",
    "%vlocity_namespace%__ObjectTypeId__c": {
        "%vlocity_namespace%__GlobalKey__c": "de201688f5bf0aaffc7cbf6c55ab0f02",
        "VlocityDataPackType": "VlocityLookupMatchingKeyObject",
        "VlocityLookupRecordSourceKey": "%vlocity_namespace%__ObjectClass__c/de201688f5bf0aaffc7cbf6c55ab0f02",
        "VlocityRecordSObjectType": "%vlocity_namespace%__ObjectClass__c"
    },
    "%vlocity_namespace%__ObjectTypeName__c": "Cloud Service Product Spec",
    "%vlocity_namespace%__ParentClassId__c": "",
    "%vlocity_namespace%__PriceListEntry__c": "Smart-Hub-Cloud-Backup_PriceListEntries.json",
    "%vlocity_namespace%__ProductChildItem__c": "Smart-Hub-Cloud-Backup_ProductChildItems.json",
    "%vlocity_namespace%__ProductSpecId__c": "",
    "%vlocity_namespace%__ProductTemplateProductId__c": "",
    "%vlocity_namespace%__Scope__c": "Order Item",
    "%vlocity_namespace%__SellingEndDate__c": "",
    "%vlocity_namespace%__SellingStartDate__c": "2017-09-01T07:00:00.000Z",
    "%vlocity_namespace%__SpecificationSubType__c": "",
    "%vlocity_namespace%__SpecificationType__c": "Product",
    "%vlocity_namespace%__StandardPremium__c": "",
    "%vlocity_namespace%__Status__c": "Active",
    "%vlocity_namespace%__SubType__c": "",
    "%vlocity_namespace%__TimeToLive__c": "",
    "%vlocity_namespace%__TrackAsAgreement__c": false,
    "%vlocity_namespace%__Type__c": "",
    "%vlocity_namespace%__VendorAccountId__c": "",
    "%vlocity_namespace%__VersionEndDateTime__c": "",
    "%vlocity_namespace%__VersionLabel__c": "V1",
    "%vlocity_namespace%__VersionStartDateTime__c": "",
    "CanUseQuantitySchedule": false,
    "CanUseRevenueSchedule": false,
    "Description": "Ensure your valuable data assets are secure in the cloud, no matter what happens!",
    "DisplayUrl": "",
    "ExternalDataSourceId": "",
    "ExternalId": "",
    "Family": "",
    "IsActive": true,
    "IsArchived": false,
    "Name": "Smart Hub Cloud Backup",
    "NumberOfQuantityInstallments": "",
    "NumberOfRevenueInstallments": "",
    "PricebookEntry": "Smart-Hub-Cloud-Backup_PricebookEntries.json",
    "ProductCode": "C-SMC-001",
    "QuantityInstallmentPeriod": "",
    "QuantityScheduleType": "",
    "QuantityUnitOfMeasure": "",
    "RecordTypeId": {
        "DeveloperName": "Product",
        "SobjectType": "Product2",
        "VlocityDataPackType": "VlocityLookupMatchingKeyObject",
        "VlocityLookupRecordSourceKey": "RecordType/Product2/Product",
        "VlocityRecordSObjectType": "RecordType"
    },
    "RevenueInstallmentPeriod": "",
    "RevenueScheduleType": "",
    "StandardPricebookEntry": [
        {
            "%vlocity_namespace%__FloorPrice__c": "",
            "%vlocity_namespace%__OverageCharge__c": "",
            "%vlocity_namespace%__OverageUOM__c": "",
            "%vlocity_namespace%__RecurringPrice__c": 0,
            "%vlocity_namespace%__RecurringUOM__c": "Monthly",
            "IsActive": true,
            "IsArchived": false,
            "Name": "Smart Hub Cloud Backup",
            "Pricebook2.Name": "Standard Price Book",
            "Pricebook2Id": {
                "Name": "Standard Price Book",
                "VlocityDataPackType": "VlocityLookupMatchingKeyObject",
                "VlocityLookupRecordSourceKey": "Pricebook2/Standard Price Book",
                "VlocityRecordSObjectType": "Pricebook2"
            },
            "Product2.%vlocity_namespace%__GlobalKey__c": "147500f4-1fce-bca1-e77b-d684c5441e1f",
            "Product2Id": {
                "%vlocity_namespace%__GlobalKey__c": "147500f4-1fce-bca1-e77b-d684c5441e1f",
                "VlocityDataPackType": "VlocityMatchingKeyObject",
                "VlocityMatchingRecordSourceKey": "Product2/147500f4-1fce-bca1-e77b-d684c5441e1f",
                "VlocityRecordSObjectType": "Product2"
            },
            "ProductCode": "C-SMC-001",
            "UnitPrice": 0,
            "UseStandardPrice": false,
            "VlocityDataPackType": "SObject",
            "VlocityRecordSObjectType": "PricebookEntry",
            "VlocityRecordSourceKey": "PricebookEntry/Pricebook2/Standard Price Book/Product2/147500f4-1fce-bca1-e77b-d684c5441e1f"
        }
    ],
    "StockKeepingUnit": "",
    "VlocityDataPackType": "SObject",
    "VlocityRecordSObjectType": "Product2",
    "VlocityRecordSourceKey": "Product2/147500f4-1fce-bca1-e77b-d684c5441e1f"
}