{
    "%vlocity_namespace%__DestinationFieldName__c": "PricebookEntryId",
    "%vlocity_namespace%__DestinationSObjectType__c": "QuoteLineItem",
    "%vlocity_namespace%__SourceFieldName__c": "%vlocity_namespace%__PricebookEntryId__c",
    "%vlocity_namespace%__SourceFieldSObjectType__c": "",
    "%vlocity_namespace%__SourceFieldType__c": "Id",
    "%vlocity_namespace%__SourceSObjectType__c": "Asset",
    "Name": "Asset>QuoteLineItem28",
    "VlocityDataPackType": "SObject",
    "VlocityRecordSObjectType": "%vlocity_namespace%__CustomFieldMap__c",
    "VlocityRecordSourceKey": "%vlocity_namespace%__CustomFieldMap__c/Asset>QuoteLineItem28"
}