{
    "%vlocity_namespace%__Description__c": "Enabling this setting would ensure that we are tracking Cataloglevel changes batch jobs contextEligibility generator , getOffers, getContainsOffers for CacheManagement.",
    "%vlocity_namespace%__SetupValue__c": "False",
    "Name": "CacheAPI.RegenerateBatchCacheProcessor",
    "VlocityDataPackType": "SObject",
    "VlocityRecordSObjectType": "%vlocity_namespace%__CpqConfigurationSetup__c",
    "VlocityRecordSourceKey": "%vlocity_namespace%__CpqConfigurationSetup__c/CacheAPI.RegenerateBatchCacheProcessor"
}